musicntwrk/__init__.py
musicntwrk/musicntwrk.py
musicntwrk/comptools/MidiFile.py
musicntwrk/comptools/displayNotes.py
musicntwrk/comptools/genmidi.py
musicntwrk/comptools/music.py
musicntwrk/comptools/notation.py
musicntwrk/data/MIDImap.py
musicntwrk/data/MIDImidi.py
musicntwrk/data/MIDIscore.py
musicntwrk/data/WRITEscore.py
musicntwrk/data/WRITEscoreNoTime.py
musicntwrk/data/WRITEscoreOps.py
musicntwrk/data/WRITEscoreOpsMIDI.py
musicntwrk/data/__init__.py
musicntwrk/data/analyzeSound.py
musicntwrk/data/analyzeTimbre.py
musicntwrk/data/ctcsound.py
musicntwrk/data/i_spectral.py
musicntwrk/data/i_spectral2.py
musicntwrk/data/i_spectral_pure.py
musicntwrk/data/i_spectral_pyo.py
musicntwrk/data/i_time_series.py
musicntwrk/data/r_1Ddata.py
musicntwrk/data/scaleMapping.py
musicntwrk/harmony/__init__.py
musicntwrk/harmony/applyOps.py
musicntwrk/harmony/changePoint.py
musicntwrk/harmony/chinese_postman.py
musicntwrk/harmony/enharmonicDictionary.py
musicntwrk/harmony/getRN.py
musicntwrk/harmony/harmonicDesign.py
musicntwrk/harmony/keySections.py
musicntwrk/harmony/lookupOps.py
musicntwrk/harmony/lookupProgr.py
musicntwrk/harmony/lookupWrapper.py
musicntwrk/harmony/networkHarmonyGen.py
musicntwrk/harmony/plotHarmonicTable.py
musicntwrk/harmony/rhythmicDesign.py
musicntwrk/harmony/scoreAnalysis.py
musicntwrk/harmony/scoreDesign.py
musicntwrk/harmony/scoreFilter.py
musicntwrk/harmony/shortHands.py
musicntwrk/harmony/showAnalysis.py
musicntwrk/harmony/spiralChordSpace.py
musicntwrk/harmony/tonalAnalysis.py
musicntwrk/harmony/tonalHarmonyCalculator.py
musicntwrk/harmony/tonalHarmonyModels.py
musicntwrk/harmony/tonalPartition.py
musicntwrk/harmony/tonnentz.py
musicntwrk/ml_utils/__init__.py
musicntwrk/ml_utils/checkRun.py
musicntwrk/ml_utils/modelDump.py
musicntwrk/ml_utils/modelLoad.py
musicntwrk/ml_utils/multiModelPredictor.py
musicntwrk/ml_utils/prepareDataSet.py
musicntwrk/ml_utils/readModels.py
musicntwrk/ml_utils/scaleDataSet.py
musicntwrk/ml_utils/trainCNNmodel.py
musicntwrk-2.3.15.dist-info/METADATA
musicntwrk-2.3.15.dist-info/WHEEL
musicntwrk-2.3.15.dist-info/top_level.txt
musicntwrk-2.3.15.dist-info/RECORD
