Metadata-Version: 2.4
Name: musicntwrk
Version: 2.3.15
Summary: music as data, data as music
Home-page: https://www.musicntwrk.com
Author: Marco Buongiorno Nardelli
Author-email: mbn@unt.edu
Platform: OS independent
Requires-Dist: numpy
Requires-Dist: scipy
Requires-Dist: pandas
Requires-Dist: python-louvain
Requires-Dist: networkx
Requires-Dist: music21
Requires-Dist: librosa
Requires-Dist: numba
Requires-Dist: pyo
Requires-Dist: matplotlib
Requires-Dist: tensorflow
Requires-Dist: powerlaw
Requires-Dist: vpython
Requires-Dist: wget
Requires-Dist: PySimpleGUI
Requires-Dist: pydub
Requires-Dist: ruptures
Requires-Dist: plotly
Provides-Extra: with-mpi
Requires-Dist: mpi4py; extra == "with-mpi"
Dynamic: author
Dynamic: author-email
Dynamic: description
Dynamic: description-content-type
Dynamic: home-page
Dynamic: platform
Dynamic: provides-extra
Dynamic: requires-dist
Dynamic: summary
